MANIFEST.in
setup.cfg
setup.py
graphite/__init__.py
graphite.theme.egg-info/PKG-INFO
graphite.theme.egg-info/SOURCES.txt
graphite.theme.egg-info/dependency_links.txt
graphite.theme.egg-info/entry_points.txt
graphite.theme.egg-info/namespace_packages.txt
graphite.theme.egg-info/not-zip-safe
graphite.theme.egg-info/requires.txt
graphite.theme.egg-info/top_level.txt
graphite/theme/__init__.py
graphite/theme/configure.zcml
graphite/theme/interfaces.py
graphite/theme/layout.py
graphite/theme/tests.py
graphite/theme/profiles/default/browserlayer.xml
graphite/theme/profiles/default/cssregistry.xml
graphite/theme/profiles/default/jsregistry.xml
graphite/theme/profiles/default/metadata.xml
graphite/theme/profiles/default/theme.xml
graphite/theme/resources/inactive.html
graphite/theme/resources/index.html
graphite/theme/resources/manifest.cfg
graphite/theme/resources/preview.png
graphite/theme/resources/rules.xml
graphite/theme/resources/css/graphite.theme.iefixes.css
graphite/theme/resources/css/graphite.theme.inactive.css
graphite/theme/resources/css/graphite.theme.ionicons.css
graphite/theme/resources/css/graphite.theme.main.css
graphite/theme/resources/fonts/ionicons.eot
graphite/theme/resources/fonts/ionicons.svg
graphite/theme/resources/fonts/ionicons.ttf
graphite/theme/resources/fonts/ionicons.woff
graphite/theme/resources/fonts/opensans-condensedlight.woff
graphite/theme/resources/fonts/opensans-light.woff
graphite/theme/resources/fonts/opensans-semibold.woff
graphite/theme/resources/fonts/opensans.woff
graphite/theme/resources/fonts/titilliumweb-regular.woff
graphite/theme/resources/fonts/titilliumweb-semibold.woff
graphite/theme/resources/images/arimport.png
graphite/theme/resources/images/arrow-right.png
graphite/theme/resources/images/logo-naralabs.png
graphite/theme/resources/images/nav-toggle-ico.png
graphite/theme/resources/js/graphite.theme.inactive.js
graphite/theme/resources/js/graphite.theme.main.js
graphite/theme/resources/overrides/plone.app.layout.viewlets.path_bar.pt
graphite/theme/upgrade/00090001.py
graphite/theme/upgrade/010100.py
graphite/theme/upgrade/010200.py
graphite/theme/upgrade/__init__.py
graphite/theme/upgrade/configure.zcml