Metadata-Version: 1.1
Name: graphite.theme
Version: 1.2
Summary: Graphite Theme for Bika OS LIMS
Home-page: http://github.com/naralabs/graphite.theme
Author: Naralabs
Author-email: info@naralabs.com
License: GPL
Keywords: diazo,theme,lims,bika,opensource
Platform: UNKNOWN
Classifier: Framework :: Plone
Classifier: Programming Language :: Python
